finesse_benchmark_database/__init__.py
finesse_benchmark_database/chunker.py
finesse_benchmark_database/config.py
finesse_benchmark_database/main.py
finesse_benchmark_database/writer.py
finesse_benchmark_database-0.1.12.dist-info/licenses/licence
finesse_benchmark_database-0.1.12.dist-info/METADATA
finesse_benchmark_database-0.1.12.dist-info/WHEEL
finesse_benchmark_database-0.1.12.dist-info/RECORD
